odoo9_addon_sale_order_price_recalculation-9.0.1.0.0-py2.7-nspkg.pth
odoo9_addon_sale_order_price_recalculation-9.0.1.0.0.dist-info/top_level.txt
odoo9_addon_sale_order_price_recalculation-9.0.1.0.0.dist-info/WHEEL
odoo9_addon_sale_order_price_recalculation-9.0.1.0.0.dist-info/RECORD
odoo9_addon_sale_order_price_recalculation-9.0.1.0.0.dist-info/metadata.json
odoo9_addon_sale_order_price_recalculation-9.0.1.0.0.dist-info/DESCRIPTION.rst
odoo9_addon_sale_order_price_recalculation-9.0.1.0.0.dist-info/METADATA
odoo9_addon_sale_order_price_recalculation-9.0.1.0.0.dist-info/namespace_packages.txt
odoo_addons/sale_order_price_recalculation/__openerp__.py
odoo_addons/sale_order_price_recalculation/__init__.py
odoo_addons/sale_order_price_recalculation/README.rst
odoo_addons/sale_order_price_recalculation/models/sale_order.py
odoo_addons/sale_order_price_recalculation/models/__init__.py
odoo_addons/sale_order_price_recalculation/i18n/zh_CN.po
odoo_addons/sale_order_price_recalculation/i18n/it.po
odoo_addons/sale_order_price_recalculation/i18n/es.po
odoo_addons/sale_order_price_recalculation/i18n/tr.po
odoo_addons/sale_order_price_recalculation/i18n/hr.po
odoo_addons/sale_order_price_recalculation/i18n/sale_order_price_recalculation.pot
odoo_addons/sale_order_price_recalculation/i18n/sl.po
odoo_addons/sale_order_price_recalculation/i18n/es_ES.po
odoo_addons/sale_order_price_recalculation/i18n/nl.po
odoo_addons/sale_order_price_recalculation/i18n/de.po
odoo_addons/sale_order_price_recalculation/i18n/fr.po
odoo_addons/sale_order_price_recalculation/i18n/fi.po
odoo_addons/sale_order_price_recalculation/views/sale_order_view.xml
odoo_addons/sale_order_price_recalculation/tests/test_sale_order_price_recalculation.py
odoo_addons/sale_order_price_recalculation/tests/__init__.py
odoo_addons/sale_order_price_recalculation/static/description/sale_order_price_recalculation.png
odoo_addons/sale_order_price_recalculation/static/description/icon.png
